<annotation>
	<folder>todownloadonpc</folder>
	<filename>00095.JPG</filename>
	<path>F:\fyp_resized_train_location_dataset\data\images\train\todownloadonpc\00095.JPG</path>
	<source>
		<database>Unknown</database>
	</source>
	<size>
		<width>800</width>
		<height>600</height>
		<depth>3</depth>
	</size>
	<segmented>0</segmented>
	<object>
		<name>pillar</name>
		<pose>Unspecified</pose>
		<truncated>0</truncated>
		<difficult>0</difficult>
		<bndbox>
			<xmin>135</xmin>
			<ymin>154</ymin>
			<xmax>186</xmax>
			<ymax>364</ymax>
		</bndbox>
	</object>
	<object>
		<name>pillar</name>
		<pose>Unspecified</pose>
		<truncated>0</truncated>
		<difficult>0</difficult>
		<bndbox>
			<xmin>266</xmin>
			<ymin>194</ymin>
			<xmax>338</xmax>
			<ymax>362</ymax>
		</bndbox>
	</object>
	<object>
		<name>Block D Pillar 4</name>
		<pose>Unspecified</pose>
		<truncated>1</truncated>
		<difficult>0</difficult>
		<bndbox>
			<xmin>8</xmin>
			<ymin>4</ymin>
			<xmax>800</xmax>
			<ymax>505</ymax>
		</bndbox>
	</object>
</annotation>
