<annotation>
	<folder>train</folder>
	<filename>108.JPG</filename>
	<path>F:\fyp_train\train\108.JPG</path>
	<source>
		<database>Unknown</database>
	</source>
	<size>
		<width>800</width>
		<height>600</height>
		<depth>3</depth>
	</size>
	<segmented>0</segmented>
	<object>
		<name>pillar</name>
		<pose>Unspecified</pose>
		<truncated>0</truncated>
		<difficult>0</difficult>
		<bndbox>
			<xmin>213</xmin>
			<ymin>176</ymin>
			<xmax>267</xmax>
			<ymax>381</ymax>
		</bndbox>
	</object>
	<object>
		<name>pillar</name>
		<pose>Unspecified</pose>
		<truncated>0</truncated>
		<difficult>0</difficult>
		<bndbox>
			<xmin>347</xmin>
			<ymin>208</ymin>
			<xmax>444</xmax>
			<ymax>371</ymax>
		</bndbox>
	</object>
	<object>
		<name>pillar</name>
		<pose>Unspecified</pose>
		<truncated>0</truncated>
		<difficult>0</difficult>
		<bndbox>
			<xmin>511</xmin>
			<ymin>265</ymin>
			<xmax>544</xmax>
			<ymax>367</ymax>
		</bndbox>
	</object>
	<object>
		<name>pillar</name>
		<pose>Unspecified</pose>
		<truncated>1</truncated>
		<difficult>0</difficult>
		<bndbox>
			<xmin>749</xmin>
			<ymin>107</ymin>
			<xmax>800</xmax>
			<ymax>376</ymax>
		</bndbox>
	</object>
	<object>
		<name>Block D corridor</name>
		<pose>Unspecified</pose>
		<truncated>0</truncated>
		<difficult>0</difficult>
		<bndbox>
			<xmin>9</xmin>
			<ymin>2</ymin>
			<xmax>795</xmax>
			<ymax>596</ymax>
		</bndbox>
	</object>
</annotation>
